prettyterm/__init__.py
prettyterm/logger.py
prettyterm/pbar.py
prettyterm/table.py
prettyterm-0.2.4.dist-info/METADATA
prettyterm-0.2.4.dist-info/WHEEL
prettyterm-0.2.4.dist-info/licenses/LICENSE
prettyterm-0.2.4.dist-info/RECORD
