Metadata-Version: 2.4
Name: prettyterm
Version: 0.2.4
Summary: Pretty terminal utilities wrapped around rich: colorful progress bars, dict-to-table printing, and more.
Author-email: Zhiyuan Ding <zhiyuanding01@gmail.com>
License: MIT
License-File: LICENSE
Requires-Python: >=3.9
Requires-Dist: colorlog>=6.0.0
Requires-Dist: rich>=13.0.0
